<?xml version="1.0" encoding="UTF-8"?>
<texte>
	<text name="nintendo_url" type="string"><![CDATA[http://www.nintendo.com]]></text>
	
	<text name="footer_impressum" type="string"><![CDATA[Terms of use]]></text>
	<text name="footer_copyright" type="string"><![CDATA[© 2000-2007 Nintendo and extra toxic. All rights reserved.]]></text>

	<text name="menu_feedback_title" type="string">FEEDBACK</text>
	<text name="menu_team_title" type="string">TEAMINFO</text>
	<text name="menu_downloads_title" type="string">DOWNLOADS</text>
	<text name="menu_hilfe_title" type="string">HELP</text>
	
	<text name="teaminfo_namen_title" type="string">NAME THE CHICKS:</text>
	<text name="teaminfo_1_names" type="string">Your team,Christiane,Bogac,Steve,Christine,Fabian</text>	
	<text name="teaminfo_2_names" type="string">Poster Bunny,Chick 1,Chick 2,Chick 3,Chick 4,Chick 5</text>	
	<text name="teaminfo_rekorde_title" type="string">YOUR RECORDS:</text>
	<text name="teaminfo_rekorde_kills" type="string">Max. # of knocked out chicks per game (pro mode)</text>
	<text name="teaminfo_rekorde_thunderbolt" type="string">Best attack: lightning</text>
	<text name="teaminfo_rekorde_weight" type="string">Best attack: weight</text>
	<text name="teaminfo_rekorde_bomb" type="string">Best attack: bomb</text>
	<text name="teaminfo_rekorde_mushroom" type="string">Best attack: toadstool</text>	
	<text name="teaminfo_rekorde_balloon" type="string">Best attack: balloon</text>
	<text name="teaminfo_rekorde_highscore" type="string">High score:</text>	
	<text name="teaminfo_rekorde_reset" type="string">Erase records</text>	
	<text name="teaminfo_rekorde_resetnote" type="string">Do you really want to erase your records?</text>
	
	<text name="gameinfo_more" type="string">More info</text>

	<text name="gameinfo_1_title" type="string">Mario Plays The #1 Black People Sport</text>
	<text name="gameinfo_1_link" type="string"><![CDATA[http://marioslambasketball.nintendo.co.uk/enGB/]]></text>	
	<text name="gameinfo_1_body" type="string">Mario and friends decide that its a good idea to play sports meant for niggas, when he is quite obviously a white male.</text>
	<text name="gameinfo_2_title" type="string">Kororinpa</text>
	<text name="gameinfo_2_link" type="string"><![CDATA[http://wii.nintendo.co.uk/7439.html]]></text>	
	<text name="gameinfo_2_body" type="string">Let's be honest here, NOBODY knows what this game is, but it might be good.</text>
	<text name="gameinfo_3_title" type="string">Pokémon Ranger</text>
	<text name="gameinfo_3_link" type="string"><![CDATA[http://ms.nintendo-europe.com/pokemonranger/enGB/index.html]]></text>	
	<text name="gameinfo_3_body" type="string"><![CDATA[Pokémon Ranger is a new type of Pokémon game made especially for Nintendo DS. Instead of playing a Pokémon Trainer you play a Ranger, responsible for protecting Pokémon in the wild. Capturing Pokémon is also handled in a whole new way; using a Capture Styler you must catch Pokémon by quickly drawing circles around them with your stylus.]]></text>
	<text name="gameinfo_4_title" type="string">Wii Channels</text>
	<text name="gameinfo_4_link" type="string"><![CDATA[http://wii.nintendo.co.uk/24.html]]></text>	
	<text name="gameinfo_4_body" type="string"><![CDATA[One of the development concepts for Wii was the idea of “increasing the number of channels on the family TV set.” Of course, since Wii is a game console, the idea of booting up a game disc in order to play games has been left intact, but much in the same way that we incorporated the internal PictoChat software on the Nintendo DS, we have also prepared some internal software for Wii.]]></text>
	<text name="gameinfo_5_title" type="string">Phoenix Wright 2</text>
	<text name="gameinfo_5_link" type="string"><![CDATA[http://www.nintendo-europe.com/NOE/en/GB/games/gamepage.do?ElementId=stn2LO1N1rjfd3--vYIiP0Uf52OiWSeb]]></text>	
	<text name="gameinfo_5_body" type="string"><![CDATA[Ace Attorney Phoenix Wright rises once again to protect the innocent and punish the lawbreakers in this sequel to one of the most surprising and original Nintendo DS hits of 2006. 'Justice for All' presents you with four new cases to investigate, each one highly complex and packed with a colourful cast of characters.]]></text>
	<text name="gameinfo_6_title" type="string">Wario Ware: Smooth Moves</text>	
	<text name="gameinfo_6_link" type="string"><![CDATA[http://wii.nintendo.co.uk/278.html]]></text>	
	<text name="gameinfo_6_body" type="string"><![CDATA[The Wario Ware team took an idea so wacky, it could only be made with the latest technology... the Wii Remote. With about 200 lightning-quick microgames and controls that range from scribbling to flailing, WarioWare: Smooth Moves takes interactive gaming to a whole new level. All players need is a Wii Remote and their best moves to be the champ.]]></text>
	<text name="gameinfo_7_title" type="string">Hotel Dusk: Room 215</text>
	<text name="gameinfo_7_link" type="string"><![CDATA[http://www.nintendo-europe.com/NOE/en/GB/games/gamepage.do?ElementId=m-R1JwUpBsj2EpdfwFIuTS7Am2I5aJLg]]></text>	
	<text name="gameinfo_7_body" type="string"><![CDATA[Los Angeles, 1979. Players take the role of Kyle Hyde, an ex-cop turned salesman trying to track down a missing friend. Clues lead to an eerie, old hotel rumored to have one very strange room – a room where wishes are granted. Players check in and get ready for a night of surprises as they try to unravel the mystery in Hotel Dusk: Room 215, a gritty new graphic adventure for the Nintendo DS.]]></text>
	<text name="gameinfo_8_title" type="string">Wii Sports</text>
	<text name="gameinfo_8_link" type="string"><![CDATA[http://wii.nintendo.co.uk/238.html]]></text>	
	<text name="gameinfo_8_body" type="string"><![CDATA[Wii Sports offers five distinct sports experiences, each using the Wii Remote to provide a natural, intuitive and realistic feel. Players can use their own Mii caricatures in the game and play them against their friends' Miis for a more personalised experience. As players improve, their Miis' skill levels will increase, so that they can see exactly how much better they've become.]]></text>
	<text name="gameinfo_9_title" type="string">Harvest Moon DS</text>
	<text name="gameinfo_9_link" type="string"><![CDATA[http://www.nintendo-europe.com/NOE/en/GB/games/gamepage.do?ElementId=Wva3b-vPr4ljPoa2cDIXhlsB0tjP__lb]]></text>	
	<text name="gameinfo_9_body" type="string"><![CDATA[Go back to the farm in the most hands-on Harvest Moon yet! Harvest Moon DS brings all the fun of the much-loved farming RPG to the dual-screened system; with touch control that lets you brush horses, shear sheep and milk cows! Living the life of a farmer you'll sow crops, tend to your livestock and even take a wife to share your dreams of rural happiness.]]></text>
	<text name="gameinfo_10_title" type="string">P Diddy Racing DS</text>
	<text name="gameinfo_10_link" type="string"><![CDATA[http://www.nintendo-europe.com/NOE/en/GB/games/gamepage.do?ElementId=9_YK-SP9sKnowUJqp795LWtYbZu6VDEo]]></text>	
	<text name="gameinfo_10_body" type="string">P Diddy Racing DS is a return to the P Diddy Racing games. Get new power ups, like baby oil traps, and a glock 18!</text>		
	
	<text name="downloads_title" type="string">Downloads achieved:</text>
	<text name="downloads_bonus" type="string">Secret download</text>
	<text name="downloads_bonusactivated" type="string">Secret download acquired!</text>
	<text name="downloads_note" type="string"><![CDATA[Problems with the download? Turn off your browser’s pop-up blocker and try again.]]></text>	
	
	<text name="feedback_name" type="string">YOUR NAME:</text>
	<text name="feedback_email" type="string">YOUR EMAIL ADDRESS: (optional)</text>
	<text name="feedback_message" type="string">Let us know what you liked and didn’t like about CHICK CHICK BOOM. We won't actually look at the shit you send us, because this email is long dead!</text>
	<text name="feedback_danke" type="string">Uh oh, the email fucked up. that's what happens when you try to use features in an 18 year old flash game.</text>
	
	<text name="help_title" type="string">Help</text>
	<text name="help_body" type="string"><![CDATA[Move the mouse over the sensitive areas to get more information.]]></text>
	<text name="help_chick_title" type="string">Your chicks</text>
	<text name="help_chick_body" type="string"><![CDATA[You have to protect your five chicks from Poster Bunny’s attacks. The game is over as soon as your last chick is knocked out.]]></text>
	<text name="help_egg_title" type="string">The egg</text>
	<text name="help_egg_body" type="string"><![CDATA[Trace the symbol on the egg to activate your attack or defense. The better your drawing is, the stronger your attack or defense.]]></text>
	<text name="help_enemychicks_title" type="string">Poster Bunny’s chicks</text>
	<text name="help_enemychicks_body" type="string"><![CDATA[Knock out the opposing chicks with your attacks.]]></text>
	<text name="help_defense_title" type="string">Your defenses</text>
	<text name="help_defense_body" type="string"><![CDATA[On the left side, you will find the symbols you can use to protect your chicks from attacks.]]></text>
	<text name="help_offense_title" type="string">Your attacks</text>
	<text name="help_offense_body" type="string"><![CDATA[On the right side, you will find the attack symbols.]]></text>
	<text name="help_bomb_title" type="string">The bomb</text>
	<text name="help_bomb_body" type="string"><![CDATA[Throw a bomb over the fence. The explosion can hit several chicks.]]></text>
	<text name="help_weight_title" type="string">The weight</text>
	<text name="help_weight_body" type="string"><![CDATA[Make a huge weight fall upon the chicks.]]></text>
	<text name="help_attract_title" type="string">The direction arrows</text>
	<text name="help_attract_body" type="string"><![CDATA[Send your chicks to the right or left corner to save them from attacks by a bomb or a weight.]]></text>
	<text name="help_mushrooms_title" type="string">The toadstool</text>
	<text name="help_mushrooms_body" type="string"><![CDATA[Make poisonous toadstools grow. Chicks that eat these become sluggish, with energy draining continuously.]]></text>
	<text name="help_mushroomkiller_title" type="string">The medicine</text>
	<text name="help_mushroomkiller_body" type="string"><![CDATA[Use the medicine to heal chicks poisoned by the toadstools.]]></text>
	<text name="help_cloud_title" type="string">The cloud</text>
	<text name="help_cloud_body" type="string"><![CDATA[Occasionally, clouds will appear and start to rain. When this happens, energy spending earthworms will pop up. The rain will also extinguish bomb fuses.]]></text>
	<text name="help_thunderbolt_title" type="string">The lightning</text>
	<text name="help_thunderbolt_body" type="string"><![CDATA[When the color of the clouds change to grey, lightning attacks are probable. Make sure you don’t strike your own chicks with the lightning.]]></text>
	<text name="help_arrester_title" type="string">The lightning rod</text>
	<text name="help_arrester_body" type="string"><![CDATA[Use the lightning rod to protect your chicks from lightning attacks.]]></text>
	<text name="help_balloon_title" type="string">The balloon</text>
	<text name="help_balloon_body" type="string"><![CDATA[If a chick gets into a balloon and floats out of sight, the chick will be lost forever.]]></text>
	<text name="help_balloonkiller_title" type="string">The sandbag</text>
	<text name="help_balloonkiller_body" type="string"><![CDATA[Using sandbags, weigh the balloon down until your chick can get out.]]></text>
	
	<text name="game_level" type="string">Level</text>
	<text name="game_start" type="string">Start</text>
	<text name="game_restart" type="string">Play again</text>
	<text name="game_gameover" type="string">GAME OVER</text>
	<text name="game_backtomenu" type="string">Back to menu</text>
	<text name="game_next" type="string">Continue</text>
	<text name="game_finished_hl" type="string"><![CDATA[Level accomplished!]]></text>
	<text name="game_finished_body" type="string"><![CDATA[You can pick up your reward later at the download center.]]></text>
	<text name="game_progress" type="string">Game progress</text>
	<text name="game_reset" type="string">Erase game progress</text>
	<text name="game_resetnote" type="string">nigga do you REALLY want to do that?</text>
	
	<text name="game_intro_start" type="string"><![CDATA[Knock Poster Bunny’s chicks out!]]></text>
	<text name="game_intro_prize" type="string"><![CDATA[Reward: A wallpaper of]]></text>
	
	<text name="game_body_profi" type="string"><![CDATA[Your goal: Hang in there as long as you can and beat your own records! Your opponent receives a new chick for each one he loses.]]></text>	
	<text name="game_body_profinote" type="string"><![CDATA[You’ve solved all 10 levels! Now, continue on to the pro-mode.]]></text>
	
	<text name="game_new_record" type="string">New record!</text>
	<text name="game_bonus_sprinkler" type="string">Sprinkler activated!</text>
	<text name="game_bonus_defusekit" type="string">Bomb defusing chick activated!</text>
	<text name="game_bonus_multismash" type="string">Double smash activated!</text>
	<text name="game_bonus_helm" type="string">Hardhat activated!</text>
	<text name="game_bonus_energy" type="string">Extra energy activated!</text>	

	<text name="game_help_baddraw" type="string"><![CDATA[Your drawing was not precise enough. Please try again.]]></text>
	<text name="game_help_ready" type="string">Lesson over... now, show us what you have learned!</text>
	
	<text name="game_l1_subtitle" type="string">A solid basis</text>
	<text name="game_l1_name" type="string">Mario Slam Basketball</text>
	<text name="game_l1_help_1" type="string"><![CDATA[Click on the weight symbol.]]></text>
	<text name="game_l1_help_2" type="string"><![CDATA[Trace the template with a single line. The better you draw, the stronger is your attack.]]></text>
	<text name="game_l1_help_3" type="string"><![CDATA[Very good! Your attack will be executed now.]]></text>
	<text name="game_l1_help_4" type="string"><![CDATA[Click on the bomb symbol.]]></text>
	<text name="game_l1_help_5" type="string"><![CDATA[You must achieve at least 70%.  Otherwise, your attack will not be executed.]]></text>	
	<text name="game_l1_help_6" type="string"><![CDATA[Very good! Your attack will be executed now.]]></text>
	<text name="game_l1_help_7" type="string"><![CDATA[Click on a direction arrow.]]></text>	
	<text name="game_l1_help_8" type="string"><![CDATA[Now you can send your chicks to the right or left corner.]]></text>	
	<text name="game_l1_help_9" type="string"><![CDATA[By doing this, you save the chicks from attacks by Poster Bunny.]]></text>	
	<text name="game_l1_help_10" type="string"><![CDATA[That’s it for now.  Now, cut down Poster Bunny!]]></text>	
		
	<text name="game_l2_subtitle" type="string">It’s raining!</text>
	<text name="game_l2_name" type="string">Kororinpa</text>
	<text name="game_l2_help_1" type="string"><![CDATA[Occasionally, clouds will appear and start to rain.  When this happens, energy spending earthworms will pop up.]]></text>
	<text name="game_l2_help_2" type="string"><![CDATA[The rain will also extinguish bomb fuses.]]></text>
	
	<text name="game_l3_subtitle" type="string">1,000,000 volts</text>
	<text name="game_l3_name" type="string">Pokémon Ranger</text>
	<text name="game_l3_help_1" type="string"><![CDATA[When the color of the clouds change to grey, lightning attacks are probable. Once this happens, select the lightning symbol.]]></text>
	<text name="game_l3_help_2" type="string"><![CDATA[Make sure the cloud is on the other side.]]></text>
	<text name="game_l3_help_3" type="string"><![CDATA[Very good! Your attack will be executed now.]]></text>
	<text name="game_l3_help_4" type="string"><![CDATA[Use the lightning rod to protect your chicks from lightning attacks.]]></text>
	
	<text name="game_l4_subtitle" type="string">Get well!</text>
	<text name="game_l4_name" type="string">Wii Channels</text>
	<text name="game_l4_help_1" type="string"><![CDATA[Make poisonous toadstools grow.]]></text>
	<text name="game_l4_help_2" type="string"><![CDATA[Chicks that eat these become sluggish, with energy draining continuously.]]></text>	
	<text name="game_l4_help_3" type="string"><![CDATA[Very good! Your attack will be executed now.]]></text>
	<text name="game_l4_help_4" type="string"><![CDATA[Use the medicine to heal chicks poisoned by the toadstools.]]></text>
	
	<text name="game_l5_subtitle" type="string">High in the sky</text>
	<text name="game_l5_name" type="string">Phoenix Wright: Ace Attorney 2</text>
	<text name="game_l5_help_1" type="string"><![CDATA[Once in a balloon, a chick will float high into the sky.]]></text>
	<text name="game_l5_help_2" type="string"><![CDATA[If a chick gets into a balloon and floats out of sight, the chick will be lost forever.]]></text>	
	<text name="game_l5_help_3" type="string"><![CDATA[Very good! Your attack will be executed now.]]></text>
	<text name="game_l5_help_4" type="string"><![CDATA[Using sandbags, weigh the balloon down until your chick can get out.]]></text>
	
	<text name="game_l6_subtitle" type="string">Hardhat</text>
	<text name="game_l6_name" type="string">Wario Ware: Smooth Moves</text>
	<text name="game_l6_help_1" type="string"><![CDATA[TIP: If you knock out several chicks with one attack, one of your chicks will receive a hardhat, which will protect the chick against attacks for a short time.]]></text>
	
	<text name="game_l7_subtitle" type="string">Double smash</text>	
	<text name="game_l7_name" type="string">Hotel Dusk: Room 215</text>
	<text name="game_l7_help_1" type="string"><![CDATA[TIP: Using a single weight, hit more than one chick at once and you’ll receive two weights for your next attack.]]></text>
	
	<text name="game_l8_subtitle" type="string">Extra energy</text>
	<text name="game_l8_name" type="string">Wii Sports</text>
	<text name="game_l8_help_1" type="string"><![CDATA[TIP: When the sun is shining, quickly draw the medicine symbol and your chicks will get an immediate boost of energy.]]></text>
	
	<text name="game_l9_subtitle" type="string">Sprinkler</text>
	<text name="game_l9_name" type="string">Harvest Moon DS</text>
	<text name="game_l9_help_1" type="string"><![CDATA[TIP: Whenever a sprinkler appears, click it, as it will attract earthworms for your chicks.]]></text>
	
	<text name="game_l10_subtitle" type="string">"Bomb has been defused!"</text>			
	<text name="game_l10_name" type="string">Diddy Kong Racing DS</text>
	<text name="game_l10_help_1" type="string"><![CDATA[TIP: If your bomb hits all five opposing chicks, one of your chicks will receive a bomb defuser kit to use for a while.]]></text>
	
	<text name="game_l11_subtitle" type="string">Pro mode</text>	
	<text name="game_l11_name" type="string"></text>	
		
	<text name="impressum">
	<![CDATA[
PUBLISHER:

extra toxic GmbH & Co. KG
Hanauer Landstraße 196a
60314 Frankfurt
phone: +49 (0)69 / 48 44 00 - 40
fax: +49 (0)69 / 48 44 00 - 39
email: <a href="mailto:info@extratoxic.com"><u>info@extratoxic.com</u></a>
web: <a href="http://www.extratoxic.com" target="_blank"><u>www.extratoxic.com</u></a>

CEOs: Christiane Fritsch, Bogac Sariaydin, Steve Welz
registration office: Amtsgericht Frankfurt am Main
registration #: HRA 42957

liable associate: extra toxic Verwaltungsgesellschaft mbH
partners: Christiane Fritsch, Bogac Sariaydin, Steve Welz
registration office: Amtsgericht Frankfurt am Main
registration #: HRB 76625

VAT #: DE 814546108

DISCLAIMER:

We of course are keen to provide you only with complete, true and up-to-date information on our web sites. We are not liable for any mistakes though, should they unintentionally occur.

We are not responsible for the content of off-site web sites or any other web sites linked or linking to our web sites. The copyrights for and the responsibility concerning the content of those off-site web sites belong to their owner exclusively.

To use our web site you need the Flash Player 8 Plugin or higher.

PRIVACY:

extra toxic GmbH & Co. KG and Nintendo recognise the importance of your privacy. All information and data that you may provide - subject to your instructions to the contrary - will be retained and disclosed only in accordance with applicable national data protection laws and regulations and in any event only to the degree necessary to efficiently process your specific request. extra toxic GmbH & Co. KG and Nintendo will not collect your personal data without your consent. It is entirely your decision as to whether you would like to disclose your individually identifiable information. Your personal data will be stored securely and will not be passed to any third party or company.

COPYRIGHT:

All content on this web site, including articles, artwork, screen shots, graphics, logos, digital downloads and other files, is the property of <a href="http://www.nintendo-europe.com/NOE/en/GB/copyright/index.jsp" target="_blank"><u>Nintendo</u></a> and extra toxic GmbH & Co. KG, unless owned by a third party, and is protected by German and international copyright, trademark and other intellectual property laws. Trademarks and copyrights for third-party content are owned by the companies that market or license those products.

Complete or partial reproduction, publishing, transfer (electronically or in other ways), modification, and using of our web sites and content for public or commercial purposes is prohibited withour prior written approval. Of course we are happy about references to our web site and insofar ask for notification.

CREDITS:

Original Music & SFX by:
Fabian Del Priore
<a href="http://www.sonicminds.de" target="_blank"><u>www.sonicminds.de</u></a>
A division of Dynamedion

Servers and Loadbalancing powered by:
<a href="http://www.ping247.de" target="_blank"><u>Ping247</u></a>
Carsten Urbanski
	]]>
	</text>	
</texte>

